{"name":"Bandar Seri Coalfields - Banyan 2","district":"Ijok","region":"Selangor","units":{"count":1,"mean":2000,"median":2000,"p25":2000,"p75":2000,"min":2000,"max":2000},"rooms":null,"beds":{"5+":{"count":1,"mean":2000,"median":2000,"p25":2000,"p75":2000,"min":2000,"max":2000}},"listings":[{"p":2000,"b":"5","ba":5,"fa":2800,"seg":"unit","a":"Bandar Seri Coalfields","t":1784548840,"u":"https://www.propertyguru.com.my/property-listing/bandar-seri-coalfields-banyan-2-for-rent-by-jimmy-tan-501756053"}]}