{"name":"Bandar Seri Coalfields","district":"Ijok","region":"Selangor","units":{"count":5,"mean":2350,"median":2000,"p25":1700,"p75":3175,"min":1700,"max":4350},"rooms":null,"beds":{"4":{"count":4,"mean":2438,"median":1850,"p25":1700,"p75":3762,"min":1700,"max":4350},"5+":{"count":1,"mean":2000,"median":2000,"p25":2000,"p75":2000,"min":2000,"max":2000}},"listings":[{"p":1700,"b":"4","ba":3,"fa":1845,"seg":"unit","a":"Bandar Seri Coalfields","t":1781438262,"u":"https://www.propertyguru.com.my/property-listing/bandar-seri-coalfields-for-rent-by-chris-see-501532166"},{"p":1700,"b":"4+1","ba":3,"fa":2281,"seg":"unit","a":"Bandar Seri Coalfields","t":1784264555,"u":"https://www.propertyguru.com.my/property-listing/bandar-seri-coalfields-for-rent-by-chee-hin-501738061"},{"p":2000,"b":"5+1","ba":5,"fa":2960,"seg":"unit","a":"Bandar Seri Coalfields","t":1782972055,"u":"https://www.propertyguru.com.my/property-listing/bandar-seri-coalfields-for-rent-by-kelly-ng-501642544"},{"p":2000,"b":"4","ba":4,"fa":2180,"seg":"unit","a":"Bandar Seri Coalfields","t":1784348280,"u":"https://www.propertyguru.com.my/property-listing/bandar-seri-coalfields-for-rent-by-joanneolle-lee-501744035"},{"p":4350,"b":"4","ba":4,"fa":2850,"seg":"unit","a":"Bandar Seri Coalfields","t":1781156633,"u":"https://www.propertyguru.com.my/property-listing/bandar-seri-coalfields-for-rent-by-max-peh-501513405"}]}