{"name":"Bandar Menjalara, 62c, Gated Guarded, 22x90, Partly Furnished","district":"Bandar Menjalara","region":"Kuala Lumpur","units":{"count":2,"mean":4000,"median":4000,"p25":4000,"p75":4000,"min":4000,"max":4000},"rooms":null,"beds":{"4":{"count":2,"mean":4000,"median":4000,"p25":4000,"p75":4000,"min":4000,"max":4000}},"listings":[{"p":4000,"b":"4","ba":3,"fa":1980,"seg":"unit","a":"","t":1780725749,"u":"https://www.propertyguru.com.my/property-listing/bandar-menjalara-62c-gated-guarded-22x90-partly-furnished-for-rent-by-alven-lim-501479510"},{"p":4000,"b":"4","ba":3,"fa":1980,"seg":"unit","a":"","t":1781165216,"u":"https://www.propertyguru.com.my/property-listing/bandar-menjalara-62c-gated-guarded-22x90-partly-furnished-for-rent-by-alven-lim-501515099"}]}