{"name":"BK8","district":"Bandar Kinrara","region":"Selangor","units":{"count":8,"mean":6400,"median":7250,"p25":4675,"p75":7500,"min":4500,"max":7500},"rooms":null,"beds":{"5+":{"count":5,"mean":7400,"median":7500,"p25":7250,"p75":7500,"min":7000,"max":7500},"4":{"count":3,"mean":4733,"median":4500,"p25":4500,"p75":5200,"min":4500,"max":5200}},"listings":[{"p":4500,"b":"4+1","ba":5,"fa":2300,"seg":"unit","a":"Bandar Kinrara Seksyen 1","t":1782373457,"u":"https://www.propertyguru.com.my/property-listing/bk8-for-rent-by-ck-yee-501538815"},{"p":4500,"b":"4+1","ba":5,"fa":2437,"seg":"unit","a":"Bandar Kinrara Seksyen 1","t":1784713192,"u":"https://www.propertyguru.com.my/property-listing/bk8-for-rent-by-alvin-teh-501694230"},{"p":5200,"b":"4+1","ba":5,"fa":2500,"seg":"unit","a":"Bandar Kinrara Seksyen 1","t":1784713037,"u":"https://www.propertyguru.com.my/property-listing/bk8-for-rent-by-alvin-teh-501704781"},{"p":7000,"b":"5","ba":6,"fa":4800,"seg":"unit","a":"Bandar Kinrara Seksyen 1","t":1783692260,"u":"https://www.propertyguru.com.my/property-listing/bk8-for-rent-by-terence-wee-501699436"},{"p":7500,"b":"5","ba":4,"fa":4850,"seg":"unit","a":"Bandar Kinrara Seksyen 1","t":1784614143,"u":"https://www.propertyguru.com.my/property-listing/bk8-for-rent-by-jess-lau-500867543"},{"p":7500,"b":"5","ba":6,"fa":4500,"seg":"unit","a":"Bandar Kinrara Seksyen 1","t":1784713020,"u":"https://www.propertyguru.com.my/property-listing/bk8-for-rent-by-alvin-teh-501319308"},{"p":7500,"b":"5+2","ba":5,"fa":4850,"seg":"unit","a":"Bandar Kinrara Seksyen 1","t":1780378638,"u":"https://www.propertyguru.com.my/property-listing/bk8-for-rent-by-zane-wong-501451076"},{"p":7500,"b":"5+2","ba":5,"fa":4850,"seg":"unit","a":"Bandar Kinrara Seksyen 1","t":1781811091,"u":"https://www.propertyguru.com.my/property-listing/bk8-for-rent-by-yeoh-xi-zang-501561771"}]}