{"name":"Cameron Towers","district":"Petaling Jaya","region":"Selangor","units":{"count":2,"mean":2300,"median":2300,"p25":2100,"p75":2500,"min":2100,"max":2500},"rooms":null,"beds":{"3":{"count":2,"mean":2300,"median":2300,"p25":2100,"p75":2500,"min":2100,"max":2500}},"listings":[{"p":2100,"b":"3","ba":2,"fa":1500,"seg":"unit","a":"Bukit Gasing","t":1784306243,"u":"https://www.propertyguru.com.my/property-listing/cameron-towers-for-rent-by-paul-ng-35033589"},{"p":2500,"b":"3","ba":2,"fa":1500,"seg":"unit","a":"Bukit Gasing","t":1784355795,"u":"https://www.propertyguru.com.my/property-listing/cameron-towers-for-rent-by-don-lee-kah-hou-501744602"}]}