{"name":"Casa Residency","district":"KL City Centre","region":"Kuala Lumpur","units":{"count":11,"mean":2845,"median":2800,"p25":2800,"p75":2800,"min":2200,"max":4000},"rooms":null,"beds":{"2":{"count":10,"mean":2730,"median":2800,"p25":2775,"p75":2800,"min":2200,"max":2800},"3":{"count":1,"mean":4000,"median":4000,"p25":4000,"p75":4000,"min":4000,"max":4000}},"listings":[{"p":2200,"b":"2","ba":2,"fa":550,"seg":"unit","a":"Bukit Bintang","t":1782745639,"u":"https://www.propertyguru.com.my/property-listing/casa-residency-for-rent-by-jenny-kong-37373308"},{"p":2700,"b":"2","ba":2,"fa":708,"seg":"unit","a":"Bukit Bintang","t":1784276925,"u":"https://www.propertyguru.com.my/property-listing/casa-residency-for-rent-by-desmond-low-501464764"},{"p":2800,"b":"2","ba":2,"fa":705,"seg":"unit","a":"Bukit Bintang","t":1779839574,"u":"https://www.propertyguru.com.my/property-listing/casa-residency-for-rent-by-meifen-low-29324659"},{"p":2800,"b":"2","ba":2,"fa":708,"seg":"unit","a":"Bukit Bintang","t":1782177329,"u":"https://www.propertyguru.com.my/property-listing/casa-residency-for-rent-by-michael-au-501402096"},{"p":2800,"b":"2","ba":2,"fa":708,"seg":"unit","a":"Bukit Bintang","t":1779852951,"u":"https://www.propertyguru.com.my/property-listing/casa-residency-for-rent-by-jc-lee-501417055"},{"p":2800,"b":"2","ba":2,"fa":708,"seg":"unit","a":"Bukit Bintang","t":1780482303,"u":"https://www.propertyguru.com.my/property-listing/casa-residency-for-rent-by-jc-lee-501460606"},{"p":2800,"b":"2","ba":2,"fa":708,"seg":"unit","a":"Bukit Bintang","t":1780543525,"u":"https://www.propertyguru.com.my/property-listing/casa-residency-for-rent-by-jc-lee-501464110"},{"p":2800,"b":"2","ba":2,"fa":708,"seg":"unit","a":"Bukit Bintang","t":1780639860,"u":"https://www.propertyguru.com.my/property-listing/casa-residency-for-rent-by-jc-lee-501473607"},{"p":2800,"b":"2","ba":2,"fa":708,"seg":"unit","a":"Bukit Bintang","t":1780814381,"u":"https://www.propertyguru.com.my/property-listing/casa-residency-for-rent-by-jc-lee-501483876"},{"p":2800,"b":"2","ba":2,"fa":708,"seg":"unit","a":"Bukit Bintang","t":1781077437,"u":"https://www.propertyguru.com.my/property-listing/casa-residency-for-rent-by-mei-yee-tan-501506747"},{"p":4000,"b":"3","ba":3,"fa":1063,"seg":"unit","a":"Bukit Bintang","t":1784001189,"u":"https://www.propertyguru.com.my/property-listing/casa-residency-for-rent-by-shervenne-tan-501715734"}]}