{"name":"Corner big house for rent,Puchong IOI Mall nearest,Sunway","district":"Puchong","region":"Selangor","units":{"count":1,"mean":9900,"median":9900,"p25":9900,"p75":9900,"min":9900,"max":9900},"rooms":null,"beds":{"5+":{"count":1,"mean":9900,"median":9900,"p25":9900,"p75":9900,"min":9900,"max":9900}},"listings":[{"p":9900,"b":"6+1","ba":6,"fa":5900,"seg":"unit","a":"BANDAR PUCHONG JAYA","t":1779798431,"u":"https://www.propertyguru.com.my/property-listing/corner-big-house-for-rent-puchong-ioi-mall-nearest-sunway-for-rent-by-shu-wai-501346182"}]}