{"name":"(Corner) N'Dira Townhouse @ Sierra 12, Puchong","district":"Puchong","region":"Selangor","units":{"count":1,"mean":4000,"median":4000,"p25":4000,"p75":4000,"min":4000,"max":4000},"rooms":null,"beds":{"3":{"count":1,"mean":4000,"median":4000,"p25":4000,"p75":4000,"min":4000,"max":4000}},"listings":[{"p":4000,"b":"3","ba":3,"fa":25831971,"seg":"unit","a":"16 Sierra","t":1780110845,"u":"https://www.propertyguru.com.my/property-listing/corner-n-dira-townhouse-sierra-12-puchong-for-rent-by-jennifer-chin-501437364"}]}