{"name":"De Kiara","district":"Setia Alam","region":"Selangor","units":{"count":6,"mean":1250,"median":1250,"p25":1100,"p75":1400,"min":1100,"max":1400},"rooms":null,"beds":{"3":{"count":6,"mean":1250,"median":1250,"p25":1100,"p75":1400,"min":1100,"max":1400}},"listings":[{"p":1100,"b":"3","ba":2,"fa":800,"seg":"unit","a":"","t":1784462431,"u":"https://www.propertyguru.com.my/property-listing/de-kiara-for-rent-by-arran-sathananthar-500771498"},{"p":1100,"b":"3","ba":2,"fa":850,"seg":"unit","a":"","t":1784175592,"u":"https://www.propertyguru.com.my/property-listing/de-kiara-for-rent-by-lian-see-501638681"},{"p":1100,"b":"3","ba":2,"fa":800,"seg":"unit","a":"","t":1783493670,"u":"https://www.propertyguru.com.my/property-listing/de-kiara-for-rent-by-terence-lee-501681626"},{"p":1400,"b":"3","ba":2,"fa":800,"seg":"unit","a":"","t":1784596665,"u":"https://www.propertyguru.com.my/property-listing/de-kiara-for-rent-by-wong-yuan-kong-41768765"},{"p":1400,"b":"3","ba":2,"fa":850,"seg":"unit","a":"","t":1784731987,"u":"https://www.propertyguru.com.my/property-listing/de-kiara-for-rent-by-syafiq-zin-501398861"},{"p":1400,"b":"3","ba":2,"fa":800,"seg":"unit","a":"","t":1783610771,"u":"https://www.propertyguru.com.my/property-listing/de-kiara-for-rent-by-veni-foo-yoke-fuang-501693294"}]}