{"name":"Impian Baiduri","district":"Petaling Jaya","region":"Selangor","units":{"count":2,"mean":1110,"median":1110,"p25":900,"p75":1320,"min":900,"max":1320},"rooms":null,"beds":{"3":{"count":2,"mean":1110,"median":1110,"p25":900,"p75":1320,"min":900,"max":1320}},"listings":[{"p":900,"b":"3","ba":2,"fa":650,"seg":"unit","a":"Seksyen 51a","t":1781254420,"u":"https://www.propertyguru.com.my/property-listing/impian-baiduri-for-rent-by-edwin-tan-501522794"},{"p":1320,"b":"3","ba":2,"fa":650,"seg":"unit","a":"Seksyen 51a","t":1784506809,"u":"https://www.propertyguru.com.my/property-listing/impian-baiduri-for-rent-by-amirul-nasyriq-501402940"}]}