{"name":"Impian Bukit Tunku","district":"Bukit Tunku (Kenny Hills)","region":"Kuala Lumpur","units":{"count":4,"mean":28000,"median":28000,"p25":28000,"p75":28000,"min":28000,"max":28000},"rooms":null,"beds":{"5+":{"count":4,"mean":28000,"median":28000,"p25":28000,"p75":28000,"min":28000,"max":28000}},"listings":[{"p":28000,"b":"8","ba":7,"fa":6126,"seg":"unit","a":"","t":1782895871,"u":"https://www.propertyguru.com.my/property-listing/impian-bukit-tunku-for-rent-by-aizat-saifulrullah-500848554"},{"p":28000,"b":"8","ba":7,"fa":6126,"seg":"unit","a":"","t":1780989983,"u":"https://www.propertyguru.com.my/property-listing/impian-bukit-tunku-for-rent-by-sheikh-imran-500850853"},{"p":28000,"b":"8","ba":7,"fa":6126,"seg":"unit","a":"","t":1781157076,"u":"https://www.propertyguru.com.my/property-listing/impian-bukit-tunku-for-rent-by-absyarie-syafiq-shahrin-501293179"},{"p":28000,"b":"8","ba":7,"fa":6126,"seg":"unit","a":"","t":1782275815,"u":"https://www.propertyguru.com.my/property-listing/impian-bukit-tunku-for-rent-by-mu-izz-halim-501591991"}]}