{"name":"Kajang","district":"Kajang","region":"Selangor","units":{"count":7,"mean":2707,"median":1900,"p25":1700,"p75":3200,"min":1600,"max":6000},"rooms":null,"beds":{"4":{"count":5,"mean":2810,"median":1900,"p25":1675,"p75":4400,"min":1600,"max":6000},"3":{"count":1,"mean":1700,"median":1700,"p25":1700,"p75":1700,"min":1700,"max":1700},"5+":{"count":1,"mean":3200,"median":3200,"p25":3200,"p75":3200,"min":3200,"max":3200}},"listings":[{"p":1600,"b":"4","ba":3,"fa":1700,"seg":"unit","a":"Bandar Teknologi Kajang","t":1781020578,"u":"https://www.propertyguru.com.my/property-listing/kajang-for-rent-by-yoke-khiem-yap-501501270"},{"p":1700,"b":"3","ba":3,"fa":1600,"seg":"unit","a":"","t":1780217036,"u":"https://www.propertyguru.com.my/property-listing/kajang-for-rent-by-han-haw-ze-501442996"},{"p":1750,"b":"4","ba":3,"fa":1600,"seg":"unit","a":"","t":1782457783,"u":"https://www.propertyguru.com.my/property-listing/kajang-for-rent-by-yoke-khiem-yap-501607774"},{"p":1900,"b":"4","ba":3,"fa":2300,"seg":"unit","a":"","t":1784177286,"u":"https://www.propertyguru.com.my/property-listing/kajang-for-rent-by-yoke-khiem-yap-500797803"},{"p":2800,"b":"4","ba":5,"fa":2700,"seg":"unit","a":"","t":1782531950,"u":"https://www.propertyguru.com.my/property-listing/kajang-for-rent-by-yoke-khiem-yap-501612273"},{"p":3200,"b":"5","ba":4,"fa":3600,"seg":"unit","a":"","t":1784197815,"u":"https://www.propertyguru.com.my/property-listing/kajang-for-rent-by-yoke-khiem-yap-501734262"},{"p":6000,"b":"4+1","ba":5,"fa":4000,"seg":"unit","a":"","t":1784390601,"u":"https://www.propertyguru.com.my/property-listing/kajang-for-rent-by-chris-lew-501746958"}]}