{"name":"Kristal Villa","district":"Kajang","region":"Selangor","units":{"count":5,"mean":1410,"median":1350,"p25":1150,"p75":1700,"min":1000,"max":1800},"rooms":null,"beds":{"3":{"count":5,"mean":1410,"median":1350,"p25":1150,"p75":1700,"min":1000,"max":1800}},"listings":[{"p":1000,"b":"3","ba":2,"fa":1008,"seg":"unit","a":"","t":1783246321,"u":"https://www.propertyguru.com.my/property-listing/kristal-villa-for-rent-by-calvin-kok-501660909"},{"p":1300,"b":"3","ba":2,"fa":1008,"seg":"unit","a":"","t":1783211617,"u":"https://www.propertyguru.com.my/property-listing/kristal-villa-for-rent-by-nurul-waheeda-501658863"},{"p":1350,"b":"3","ba":2,"fa":1008,"seg":"unit","a":"","t":1781572235,"u":"https://www.propertyguru.com.my/property-listing/kristal-villa-for-rent-by-catherine-edward-501541563"},{"p":1600,"b":"3","ba":2,"fa":1008,"seg":"unit","a":"","t":1784198644,"u":"https://www.propertyguru.com.my/property-listing/kristal-villa-for-rent-by-yoke-khiem-yap-501734341"},{"p":1800,"b":"3","ba":2,"fa":1008,"seg":"unit","a":"","t":1780826290,"u":"https://www.propertyguru.com.my/property-listing/kristal-villa-for-rent-by-firdaus-dauz-40841098"}]}