{"name":"Menara Bukit Ceylon","district":"KL City Centre","region":"Kuala Lumpur","units":{"count":10,"mean":6170,"median":3800,"p25":3650,"p75":4125,"min":2900,"max":28000},"rooms":null,"beds":{"4":{"count":1,"mean":28000,"median":28000,"p25":28000,"p75":28000,"min":28000,"max":28000},"3":{"count":5,"mean":3720,"median":3800,"p25":3600,"p75":3800,"min":3500,"max":3800},"2":{"count":4,"mean":3775,"median":3850,"p25":3100,"p75":4375,"min":2900,"max":4500}},"listings":[{"p":2900,"b":"2+1","ba":2,"fa":1485,"seg":"unit","a":"Bukit Bintang","t":1782971587,"u":"https://www.propertyguru.com.my/property-listing/menara-bukit-ceylon-for-rent-by-lc-seow-501154494"},{"p":3500,"b":"3","ba":2,"fa":1500,"seg":"unit","a":"Bukit Bintang","t":1781072015,"u":"https://www.propertyguru.com.my/property-listing/menara-bukit-ceylon-for-rent-by-chen-kah-seng-501505632"},{"p":3700,"b":"2+1","ba":2,"fa":1500,"seg":"unit","a":"Bukit Bintang","t":1780073150,"u":"https://www.propertyguru.com.my/property-listing/menara-bukit-ceylon-for-rent-by-bing-bing-501436522"},{"p":3700,"b":"3","ba":2,"fa":1500,"seg":"unit","a":"Bukit Bintang","t":1783675063,"u":"https://www.propertyguru.com.my/property-listing/menara-bukit-ceylon-for-rent-by-ben-ling-501697938"},{"p":3800,"b":"3","ba":2,"fa":1500,"seg":"unit","a":"Bukit Bintang","t":1781603346,"u":"https://www.propertyguru.com.my/property-listing/menara-bukit-ceylon-for-rent-by-kweenie-chong-500115313"},{"p":3800,"b":"3","ba":2,"fa":1138,"seg":"unit","a":"Bukit Bintang","t":1782299119,"u":"https://www.propertyguru.com.my/property-listing/menara-bukit-ceylon-for-rent-by-jay-b-501424531"},{"p":3800,"b":"3","ba":2,"fa":1500,"seg":"unit","a":"Bukit Bintang","t":1782694036,"u":"https://www.propertyguru.com.my/property-listing/menara-bukit-ceylon-for-rent-by-wil-koh-501618752"},{"p":4000,"b":"2","ba":2,"fa":1500,"seg":"unit","a":"Bukit Bintang","t":1780919693,"u":"https://www.propertyguru.com.my/property-listing/menara-bukit-ceylon-for-rent-by-xiaxun-ong-501320708"},{"p":4500,"b":"2+1","ba":2,"fa":1600,"seg":"unit","a":"Bukit Bintang","t":1779894959,"u":"https://www.propertyguru.com.my/property-listing/menara-bukit-ceylon-for-rent-by-jacob-ong-501421486"},{"p":28000,"b":"4","ba":6,"fa":8000,"seg":"unit","a":"Bukit Bintang","t":1781711377,"u":"https://www.propertyguru.com.my/property-listing/menara-bukit-ceylon-for-rent-by-jean-chiew-43160121"}]}