{"name":"Pangsapuri Sri Baiduri","district":"Ampang","region":"Selangor","units":{"count":3,"mean":1050,"median":1000,"p25":1000,"p75":1150,"min":1000,"max":1150},"rooms":null,"beds":{"3":{"count":2,"mean":1000,"median":1000,"p25":1000,"p75":1000,"min":1000,"max":1000},"2":{"count":1,"mean":1150,"median":1150,"p25":1150,"p75":1150,"min":1150,"max":1150}},"listings":[{"p":1000,"b":"3","ba":2,"fa":900,"seg":"unit","a":"Ampang Jaya","t":1779703994,"u":"https://www.propertyguru.com.my/property-listing/pangsapuri-sri-baiduri-for-rent-by-jack-liew-500967935"},{"p":1000,"b":"3","ba":2,"fa":650,"seg":"unit","a":"Ampang Jaya","t":1781339664,"u":"https://www.propertyguru.com.my/property-listing/pangsapuri-sri-baiduri-for-rent-by-philip-ng-501527621"},{"p":1150,"b":"2","ba":2,"fa":900,"seg":"unit","a":"Ampang Jaya","t":1784021913,"u":"https://www.propertyguru.com.my/property-listing/pangsapuri-sri-baiduri-for-rent-by-eason-hong-501719418"}]}