{"name":"Park 51 Boulevard","district":"Petaling Jaya","region":"Selangor","units":{"count":2,"mean":1575,"median":1575,"p25":1450,"p75":1700,"min":1450,"max":1700},"rooms":null,"beds":{"Studio":{"count":2,"mean":1575,"median":1575,"p25":1450,"p75":1700,"min":1450,"max":1700}},"listings":[{"p":1450,"b":"Studio","ba":1,"fa":457,"seg":"unit","a":"","t":1779779069,"u":"https://www.propertyguru.com.my/property-listing/park-51-boulevard-for-rent-by-mindy-cheah-40683217"},{"p":1700,"b":"Studio","ba":1,"fa":475,"seg":"unit","a":"","t":1781147063,"u":"https://www.propertyguru.com.my/property-listing/park-51-boulevard-for-rent-by-sean-ng-42987030"}]}