{"name":"PJ8","district":"Petaling Jaya","region":"Selangor","units":{"count":13,"mean":2600,"median":2399,"p25":2000,"p75":3350,"min":1900,"max":3700},"rooms":null,"beds":{"1":{"count":6,"mean":2100,"median":2050,"p25":1975,"p75":2250,"min":1900,"max":2399},"4":{"count":2,"mean":3650,"median":3650,"p25":3600,"p75":3700,"min":3600,"max":3700},"2":{"count":4,"mean":3000,"median":2950,"p25":2575,"p75":3475,"min":2500,"max":3600},"Studio":{"count":1,"mean":1900,"median":1900,"p25":1900,"p75":1900,"min":1900,"max":1900}},"listings":[{"p":1900,"b":"Studio","ba":1,"fa":650,"seg":"unit","a":"Seksyen 8","t":1784639194,"u":"https://www.propertyguru.com.my/property-listing/pj8-for-rent-by-grace-yong-501481203"},{"p":1900,"b":"1","ba":1,"fa":667,"seg":"unit","a":"Seksyen 8","t":1784264048,"u":"https://www.propertyguru.com.my/property-listing/pj8-for-rent-by-terry-hing-501737950"},{"p":2000,"b":"1","ba":1,"fa":590,"seg":"unit","a":"Seksyen 8","t":1780108605,"u":"https://www.propertyguru.com.my/property-listing/pj8-for-rent-by-ml-cheong-22055189"},{"p":2000,"b":"1","ba":1,"fa":667,"seg":"unit","a":"Seksyen 8","t":1783565401,"u":"https://www.propertyguru.com.my/property-listing/pj8-for-rent-by-ivan-tan-500849496"},{"p":2100,"b":"1","ba":1,"fa":667,"seg":"unit","a":"Seksyen 8","t":1784190763,"u":"https://www.propertyguru.com.my/property-listing/pj8-for-rent-by-grace-yong-501643872"},{"p":2200,"b":"1","ba":1,"fa":667,"seg":"unit","a":"Seksyen 8","t":1784264549,"u":"https://www.propertyguru.com.my/property-listing/pj8-for-rent-by-terry-hing-501738038"},{"p":2399,"b":"1","ba":1,"fa":650,"seg":"unit","a":"Seksyen 8","t":1784135541,"u":"https://www.propertyguru.com.my/property-listing/pj8-for-rent-by-yumi-lim-500065624"},{"p":2500,"b":"2","ba":2,"fa":780,"seg":"unit","a":"Seksyen 8","t":1780486444,"u":"https://www.propertyguru.com.my/property-listing/pj8-for-rent-by-janice-low-33688233"},{"p":2800,"b":"2","ba":2,"fa":840,"seg":"unit","a":"Seksyen 8","t":1782101170,"u":"https://www.propertyguru.com.my/property-listing/pj8-for-rent-by-janice-low-36470740"},{"p":3100,"b":"2","ba":3,"fa":1152,"seg":"unit","a":"Seksyen 8","t":1784262635,"u":"https://www.propertyguru.com.my/property-listing/pj8-for-rent-by-terry-hing-501737754"},{"p":3600,"b":"4","ba":4,"fa":2000,"seg":"unit","a":"Seksyen 8","t":1781065487,"u":"https://www.propertyguru.com.my/property-listing/pj8-for-rent-by-jennifer-poon-38790750"},{"p":3600,"b":"2+2","ba":4,"fa":1850,"seg":"unit","a":"Seksyen 8","t":1784263102,"u":"https://www.propertyguru.com.my/property-listing/pj8-for-rent-by-terry-hing-501737827"},{"p":3700,"b":"4","ba":0,"fa":2000,"seg":"unit","a":"Seksyen 8","t":1781323270,"u":"https://www.propertyguru.com.my/property-listing/pj8-for-rent-by-jennifer-poon-22793879"}]}