{"name":"Starling @ Rimbayu","district":"Tanjong Duabelas","region":"Selangor","units":{"count":3,"mean":2033,"median":2200,"p25":1600,"p75":2300,"min":1600,"max":2300},"rooms":null,"beds":{"3":{"count":3,"mean":2033,"median":2200,"p25":1600,"p75":2300,"min":1600,"max":2300}},"listings":[{"p":1600,"b":"3","ba":3,"fa":1694,"seg":"unit","a":"","t":1784619478,"u":"https://www.propertyguru.com.my/property-listing/starling-rimbayu-for-rent-by-charlie-gan-501673689"},{"p":2200,"b":"3","ba":3,"fa":1807,"seg":"unit","a":"Bandar Rimbayu","t":1783301114,"u":"https://www.propertyguru.com.my/property-listing/starling-rimbayu-for-rent-by-miki-you-501663032"},{"p":2300,"b":"3","ba":3,"fa":1802,"seg":"unit","a":"","t":1784619489,"u":"https://www.propertyguru.com.my/property-listing/starling-rimbayu-for-rent-by-charlie-gan-501673571"}]}