{"name":"Sunway Rymba Hills","district":"Kota Damansara","region":"Selangor","units":{"count":9,"mean":12067,"median":12800,"p25":10750,"p75":13500,"min":7000,"max":15000},"rooms":null,"beds":{"5+":{"count":8,"mean":11975,"median":12650,"p25":10125,"p75":13750,"min":7000,"max":15000},"4":{"count":1,"mean":12800,"median":12800,"p25":12800,"p75":12800,"min":12800,"max":12800}},"listings":[{"p":7000,"b":"5+1","ba":6,"fa":4519,"seg":"unit","a":"Sunway Damansara","t":1780645838,"u":"https://www.propertyguru.com.my/property-listing/sunway-rymba-hills-for-rent-by-emily-kho-501474710"},{"p":9500,"b":"5+6","ba":7,"fa":4519,"seg":"unit","a":"Sunway Damansara","t":1781601566,"u":"https://www.propertyguru.com.my/property-listing/sunway-rymba-hills-for-rent-by-darren-leong-501546156"},{"p":12000,"b":"5+4","ba":5,"fa":4500,"seg":"unit","a":"Sunway Damansara","t":1781327950,"u":"https://www.propertyguru.com.my/property-listing/sunway-rymba-hills-for-rent-by-emily-kho-501526480"},{"p":12500,"b":"5+1","ba":6,"fa":4500,"seg":"unit","a":"Sunway Damansara","t":1784536400,"u":"https://www.propertyguru.com.my/property-listing/sunway-rymba-hills-for-rent-by-max-peh-501754499"},{"p":12800,"b":"5+1","ba":6,"fa":4529,"seg":"unit","a":"Sunway Damansara","t":1784729457,"u":"https://www.propertyguru.com.my/property-listing/sunway-rymba-hills-for-rent-by-jordan-teh-106771212"},{"p":12800,"b":"4+1","ba":6,"fa":4519,"seg":"unit","a":"Sunway Damansara","t":1784519558,"u":"https://www.propertyguru.com.my/property-listing/sunway-rymba-hills-for-rent-by-anson-ng-501567363"},{"p":13000,"b":"6","ba":7,"fa":4650,"seg":"unit","a":"Sunway Damansara","t":1782393769,"u":"https://www.propertyguru.com.my/property-listing/sunway-rymba-hills-for-rent-by-syah-othman-501604174"},{"p":14000,"b":"5","ba":6,"fa":4519,"seg":"unit","a":"Sunway Damansara","t":1783738600,"u":"https://www.propertyguru.com.my/property-listing/sunway-rymba-hills-for-rent-by-elaine-kow-29953604"},{"p":15000,"b":"5+1","ba":6,"fa":4529,"seg":"unit","a":"Sunway Damansara","t":1780963955,"u":"https://www.propertyguru.com.my/property-listing/sunway-rymba-hills-for-rent-by-emily-kho-501471724"}]}