{"name":"Taman Pantai Prima","district":"Pantai","region":"Kuala Lumpur","units":{"count":1,"mean":2100,"median":2100,"p25":2100,"p75":2100,"min":2100,"max":2100},"rooms":{"count":4,"mean":1138,"median":1100,"p25":812,"p75":1500,"min":750,"max":1600},"beds":{"2":{"count":1,"mean":2100,"median":2100,"p25":2100,"p75":2100,"min":2100,"max":2100}},"listings":[{"p":2100,"b":"2","ba":1,"fa":1300,"seg":"unit","a":"Pantai Dalam","t":1782987369,"u":"https://www.propertyguru.com.my/property-listing/taman-pantai-prima-for-rent-by-chien-koh-501408561"},{"p":750,"b":0,"ba":1,"fa":100,"seg":"room","a":"Pantai Dalam","t":1783607054,"u":"https://www.propertyguru.com.my/property-listing/taman-pantai-prima-for-rent-by-ee-tsin-lim-501692938"},{"p":1000,"b":0,"ba":1,"fa":100,"seg":"room","a":"Pantai Dalam","t":1783607185,"u":"https://www.propertyguru.com.my/property-listing/taman-pantai-prima-for-rent-by-ee-tsin-lim-501692957"},{"p":1200,"b":0,"ba":1,"fa":100,"seg":"room","a":"Pantai Dalam","t":1783607279,"u":"https://www.propertyguru.com.my/property-listing/taman-pantai-prima-for-rent-by-ee-tsin-lim-501692979"},{"p":1600,"b":0,"ba":1,"fa":100,"seg":"room","a":"Pantai Dalam","t":1783606774,"u":"https://www.propertyguru.com.my/property-listing/taman-pantai-prima-for-rent-by-ee-tsin-lim-501692902"}]}