{"name":"Taman Cheras Awana","district":"Cheras","region":"Selangor","units":{"count":2,"mean":1625,"median":1625,"p25":1500,"p75":1750,"min":1500,"max":1750},"rooms":null,"beds":{"3":{"count":1,"mean":1500,"median":1500,"p25":1500,"p75":1500,"min":1500,"max":1500},"4":{"count":1,"mean":1750,"median":1750,"p25":1750,"p75":1750,"min":1750,"max":1750}},"listings":[{"p":1500,"b":"3","ba":2,"fa":1100,"seg":"unit","a":"Taman Cheras Awana","t":1784615859,"u":"https://www.propertyguru.com.my/property-listing/taman-cheras-awana-for-rent-by-chris-chong-501725102"},{"p":1750,"b":"4","ba":3,"fa":1800,"seg":"unit","a":"Pekan Batu 9","t":1784227302,"u":"https://www.propertyguru.com.my/property-listing/taman-cheras-awana-for-rent-by-amanda-wee-501736219"}]}