{"name":"Taman Seri Bukit Segambut","district":"Batu","region":"Kuala Lumpur","units":{"count":3,"mean":3067,"median":3200,"p25":2800,"p75":3200,"min":2800,"max":3200},"rooms":null,"beds":{"3":{"count":2,"mean":3200,"median":3200,"p25":3200,"p75":3200,"min":3200,"max":3200},"4":{"count":1,"mean":2800,"median":2800,"p25":2800,"p75":2800,"min":2800,"max":2800}},"listings":[{"p":2800,"b":"4","ba":3,"fa":1400,"seg":"unit","a":"Taman Seri Bukit Segambut","t":1783466338,"u":"https://www.propertyguru.com.my/property-listing/taman-seri-bukit-segambut-for-rent-by-see-hui-tan-501678664"},{"p":3200,"b":"3","ba":3,"fa":1540,"seg":"unit","a":"Taman Seri Bukit Segambut","t":1779876293,"u":"https://www.propertyguru.com.my/property-listing/taman-seri-bukit-segambut-for-rent-by-perry-chai-501315071"},{"p":3200,"b":"3","ba":3,"fa":1540,"seg":"unit","a":"Taman Seri Bukit Segambut","t":1781058720,"u":"https://www.propertyguru.com.my/property-listing/taman-seri-bukit-segambut-for-rent-by-yubi-leong-501503741"}]}