{"name":"Taman Impian Indah","district":"Balakong","region":"Selangor","units":{"count":3,"mean":1033,"median":1000,"p25":1000,"p75":1100,"min":1000,"max":1100},"rooms":null,"beds":{"3":{"count":3,"mean":1033,"median":1000,"p25":1000,"p75":1100,"min":1000,"max":1100}},"listings":[{"p":1000,"b":"3","ba":2,"fa":850,"seg":"unit","a":"Taman Impian Indah","t":1781064873,"u":"https://www.propertyguru.com.my/property-listing/taman-impian-indah-for-rent-by-benny-lee-41575114"},{"p":1000,"b":"3","ba":2,"fa":1000,"seg":"unit","a":"Taman Impian Indah","t":1780035096,"u":"https://www.propertyguru.com.my/property-listing/taman-impian-indah-for-rent-by-rain-leow-501402997"},{"p":1100,"b":"3","ba":2,"fa":775,"seg":"unit","a":"Taman Impian Indah","t":1782205684,"u":"https://www.propertyguru.com.my/property-listing/taman-impian-indah-for-rent-by-ashley-wong-501587921"}]}