{"name":"Taman lestari putra,putra permai,seri kembangan,puncak jalil","district":"Seri Kembangan","region":"Selangor","units":{"count":1,"mean":1200,"median":1200,"p25":1200,"p75":1200,"min":1200,"max":1200},"rooms":null,"beds":{"4":{"count":1,"mean":1200,"median":1200,"p25":1200,"p75":1200,"min":1200,"max":1200}},"listings":[{"p":1200,"b":"4","ba":3,"fa":1400,"seg":"unit","a":"Bandar Putra Permai","t":1784539953,"u":"https://www.propertyguru.com.my/property-listing/taman-lestari-putra-putra-permai-seri-kembangan-puncak-jalil-for-rent-by-song-han-29224150"}]}