{"name":"The Valley TTDI","district":"Ampang","region":"Selangor","units":{"count":5,"mean":25200,"median":20000,"p25":18000,"p75":35000,"min":18000,"max":35000},"rooms":null,"beds":{"5+":{"count":5,"mean":25200,"median":20000,"p25":18000,"p75":35000,"min":18000,"max":35000}},"listings":[{"p":18000,"b":"7","ba":7,"fa":5338,"seg":"unit","a":"The Valley TTDI","t":1784532169,"u":"https://www.propertyguru.com.my/property-listing/the-valley-ttdi-for-rent-by-janice-ling-41942486"},{"p":18000,"b":"7+1","ba":8,"fa":5300,"seg":"unit","a":"The Valley TTDI","t":1781503898,"u":"https://www.propertyguru.com.my/property-listing/the-valley-ttdi-for-rent-by-marco-tan-501141952"},{"p":20000,"b":"6+1","ba":7,"fa":5350,"seg":"unit","a":"","t":1784720327,"u":"https://www.propertyguru.com.my/property-listing/the-valley-ttdi-for-rent-by-lucus-yong-501771390"},{"p":35000,"b":"8+1","ba":9,"fa":7700,"seg":"unit","a":"The Valley TTDI","t":1781004443,"u":"https://www.propertyguru.com.my/property-listing/the-valley-ttdi-for-rent-by-marco-tan-501501012"},{"p":35000,"b":"8+1","ba":9,"fa":8000,"seg":"unit","a":"","t":1784252161,"u":"https://www.propertyguru.com.my/property-listing/the-valley-ttdi-for-rent-by-lucus-yong-501555931"}]}